S3RecipeHandler/Asset.py
S3RecipeHandler/AssetList.py
S3RecipeHandler/BodyModBlock.py
S3RecipeHandler/GraphicBlock.py
S3RecipeHandler/Helpers.py
S3RecipeHandler/Model.py
S3RecipeHandler/RGBBlock.py
S3RecipeHandler/Recipe.py
S3RecipeHandler/S3RGB.py
S3RecipeHandler/__init__.py
S3RecipeHandler/graphic_vector.py
S3RecipeHandler/graphic_vector_list.py
S3RecipeHandler/texture.py
s3recipehandler-1.2.0.dist-info/licenses/LICENSE.txt
s3recipehandler-1.2.0.dist-info/METADATA
s3recipehandler-1.2.0.dist-info/WHEEL
s3recipehandler-1.2.0.dist-info/top_level.txt
s3recipehandler-1.2.0.dist-info/RECORD
