Metadata-Version: 2.4
Name: S3RecipeHandler
Version: 1.2.0
Summary: A Custom Skate 3 Recipe File Library
Author: S4M
License: GPLv3
Project-URL: Homepage, https://github.com/l-S4M-l/S3RecipeHandler
Project-URL: Bug Tracker, https://github.com/l-S4M-l/S3RecipeHandler/issues
Project-URL: Ko-fi, https://ko-fi.com/chillsam2
Classifier: Programming Language :: Python :: 3
Classifier: License :: OSI Approved :: GNU General Public License v3 (GPLv3)
Classifier: Operating System :: OS Independent
Classifier: Development Status :: 3 - Alpha
Classifier: Intended Audience :: Developers
Classifier: Topic :: Software Development :: Libraries :: Python Modules
Requires-Python: >=3.9
License-File: LICENSE.txt
Dynamic: license-file
